<?xml version="1.0" encoding="UTF-8"?>
<nexml xmlns="http://www.nexml.org/2009" xmlns:dc="http://purl.org/dc/terms/" xmlns:dwc="http://rs.tdwg.org/dwc/terms/" xmlns:obo="http://purl.obolibrary.org/obo/" xmlns:phen="http://www.bioontologies.org/obd/schema/pheno" xmlns:ps="http://vocab.phenoscape.org/" xmlns:rdfs="http://www.w3.org/2000/01/rdf-schema#" xmlns:xsi="http://www.w3.org/2001/XMLSchema-instance" generator="Phenex null" version="0.9" xsi:schemaLocation="http://www.nexml.org/2009 http://www.nexml.org/2009/nexml.xsd http://www.bioontologies.org/obd/schema/pheno http://purl.org/phenoscape/phenoxml.xsd">
  <meta xsi:type="LiteralMeta" property="dc:creator" />
  <meta xsi:type="ResourceMeta" rel="dc:source">
    <meta xsi:type="LiteralMeta" property="dc:identifier">https://doi.org/10.5281/zenodo.191105</meta>
    <meta xsi:type="LiteralMeta" property="dc:bibliographicCitation">Britz, R. (2009) Danionella priapus, a new species of miniature cyprinid fish from West Bengal, India (Teleostei: Cypriniformes: Cyprinidae). Zootaxa  2277: 53–60</meta>
    <meta xsi:type="LiteralMeta" property="dc:title">Britz (2009)</meta>
  </meta>
  <meta xsi:type="LiteralMeta" property="dc:description" />
  <otus id="t611139a1-0277-4c63-8cc6-d586f0f518e9">
    <otu id="t4c329efd-f251-48ef-b8ef-baa91e9ca0f7" label="Danionella priapus" about="#t4c329efd-f251-48ef-b8ef-baa91e9ca0f7">
      <meta xsi:type="ResourceMeta" rel="dwc:taxonID" href="http://purl.obolibrary.org/obo/VTO_0063162" />
    </otu>
  </otus>
  <characters id="07f3becc-f6da-476a-925a-db78abf22c79" xsi:type="StandardCells" otus="t611139a1-0277-4c63-8cc6-d586f0f518e9">
    <format>
      <states id="sf9469009-7a2c-4251-b3be-19a41ea1e579">
        <state id="s70694060-9eed-4442-93c8-c63248dd9d67" label="absent" symbol="0" about="#s70694060-9eed-4442-93c8-c63248dd9d67">
          <meta xsi:type="LiteralMeta" property="ps:describesPhenotype">
            <phen:phenotype>
              <phen:phenotype_character>
                <phen:bearer>
                  <phen:typeref about="UBERON:2000585" />
                </phen:bearer>
                <phen:quality>
                  <phen:typeref about="PATO:0000462" />
                </phen:quality>
              </phen:phenotype_character>
              <phen:phenotype_character>
                <phen:bearer>
                  <phen:typeref about="UBERON:2001406" />
                </phen:bearer>
                <phen:quality>
                  <phen:typeref about="PATO:0000462" />
                </phen:quality>
              </phen:phenotype_character>
            </phen:phenotype>
          </meta>
        </state>
      </states>
      <states id="s4b2c92a4-b361-40eb-a633-c22cdc0f210f">
        <state id="sc481e3f7-f37c-4bfc-926c-4830d18cffea" label="absent" symbol="0" about="#sc481e3f7-f37c-4bfc-926c-4830d18cffea">
          <meta xsi:type="LiteralMeta" property="ps:describesPhenotype">
            <phen:phenotype>
              <phen:phenotype_character>
                <phen:bearer>
                  <phen:typeref about="UBERON:2001404" />
                </phen:bearer>
                <phen:quality>
                  <phen:typeref about="PATO:0000462" />
                </phen:quality>
              </phen:phenotype_character>
            </phen:phenotype>
          </meta>
        </state>
      </states>
      <states id="s971ae930-fb51-407e-b308-2c58f049be5e">
        <state id="s42913ffc-f344-4d37-acdf-555f2e27d77f" label="absent" symbol="0" about="#s42913ffc-f344-4d37-acdf-555f2e27d77f">
          <meta xsi:type="LiteralMeta" property="ps:describesPhenotype">
            <phen:phenotype>
              <phen:phenotype_character>
                <phen:bearer>
                  <phen:typeref about="UBERON:0002396" />
                </phen:bearer>
                <phen:quality>
                  <phen:typeref about="PATO:0000462" />
                </phen:quality>
              </phen:phenotype_character>
            </phen:phenotype>
          </meta>
        </state>
      </states>
      <states id="s542293a2-19dd-43e8-8f7b-e7844772baff">
        <state id="s641e47be-46c5-42f9-9e13-880db944b1a6" label="absent" symbol="0" about="#s641e47be-46c5-42f9-9e13-880db944b1a6">
          <meta xsi:type="LiteralMeta" property="ps:describesPhenotype">
            <phen:phenotype>
              <phen:phenotype_character>
                <phen:bearer>
                  <phen:typeref about="UBERON:2002022" />
                </phen:bearer>
                <phen:quality>
                  <phen:typeref about="PATO:0000462" />
                </phen:quality>
              </phen:phenotype_character>
            </phen:phenotype>
          </meta>
        </state>
      </states>
      <states id="sb82a1563-20c3-4233-9307-dcbceba81305">
        <state id="sdd87d207-a81c-4d3b-b885-dc2e2e2b3b3c" label="absent" symbol="0" about="#sdd87d207-a81c-4d3b-b885-dc2e2e2b3b3c">
          <meta xsi:type="LiteralMeta" property="ps:describesPhenotype">
            <phen:phenotype>
              <phen:phenotype_character>
                <phen:bearer>
                  <phen:typeref about="UBERON:0001681" />
                </phen:bearer>
                <phen:quality>
                  <phen:typeref about="PATO:0000462" />
                </phen:quality>
              </phen:phenotype_character>
            </phen:phenotype>
          </meta>
        </state>
      </states>
      <states id="sf3fd0ca6-fe61-4337-bbfc-7580626980ee">
        <state id="s41d28048-1eff-49a8-bd85-881cf9997656" label="absent" symbol="0" about="#s41d28048-1eff-49a8-bd85-881cf9997656">
          <meta xsi:type="LiteralMeta" property="ps:describesPhenotype">
            <phen:phenotype>
              <phen:phenotype_character>
                <phen:bearer>
                  <phen:typeref about="UBERON:0004865" />
                </phen:bearer>
                <phen:quality>
                  <phen:typeref about="PATO:0000462" />
                </phen:quality>
              </phen:phenotype_character>
            </phen:phenotype>
          </meta>
        </state>
      </states>
      <states id="s116cec39-7c09-4da8-8697-de563b70fafb">
        <state id="sa1bae812-6370-4aaa-9e97-472d6d87d74d" label="absent" symbol="0" about="#sa1bae812-6370-4aaa-9e97-472d6d87d74d">
          <meta xsi:type="LiteralMeta" property="ps:describesPhenotype">
            <phen:phenotype>
              <phen:phenotype_character>
                <phen:bearer>
                  <phen:typeref about="UBERON:2000474" />
                </phen:bearer>
                <phen:quality>
                  <phen:typeref about="PATO:0000462" />
                </phen:quality>
              </phen:phenotype_character>
            </phen:phenotype>
          </meta>
        </state>
      </states>
      <states id="sc8210009-5c34-4122-b1ee-5979d7bb70a6">
        <state id="sf9cfa8d8-d7af-40b9-a0c3-d18bff86a115" label="absent" symbol="0" about="#sf9cfa8d8-d7af-40b9-a0c3-d18bff86a115">
          <meta xsi:type="LiteralMeta" property="ps:describesPhenotype">
            <phen:phenotype>
              <phen:phenotype_character>
                <phen:bearer>
                  <phen:typeref about="UBERON:2000663" />
                </phen:bearer>
                <phen:quality>
                  <phen:typeref about="PATO:0000462" />
                </phen:quality>
              </phen:phenotype_character>
            </phen:phenotype>
          </meta>
        </state>
      </states>
      <states id="sef65cd6b-2ac3-4d03-8e21-dbd499d7ef80">
        <state id="sac6bf7f5-cbe3-410b-92ad-b8dd24d72e7c" label="absent" symbol="0" about="#sac6bf7f5-cbe3-410b-92ad-b8dd24d72e7c">
          <meta xsi:type="LiteralMeta" property="ps:describesPhenotype">
            <phen:phenotype>
              <phen:phenotype_character>
                <phen:bearer>
                  <phen:typeref about="UBERON:2001407" />
                </phen:bearer>
                <phen:quality>
                  <phen:typeref about="PATO:0000462" />
                </phen:quality>
              </phen:phenotype_character>
              <phen:phenotype_character>
                <phen:bearer>
                  <phen:typeref about="UBERON:2001408" />
                </phen:bearer>
                <phen:quality>
                  <phen:typeref about="PATO:0000462" />
                </phen:quality>
              </phen:phenotype_character>
              <phen:phenotype_character>
                <phen:bearer>
                  <phen:typeref about="UBERON:2001409" />
                </phen:bearer>
                <phen:quality>
                  <phen:typeref about="PATO:0000462" />
                </phen:quality>
              </phen:phenotype_character>
              <phen:phenotype_character>
                <phen:bearer>
                  <phen:typeref about="UBERON:2000495" />
                </phen:bearer>
                <phen:quality>
                  <phen:typeref about="PATO:0000462" />
                </phen:quality>
              </phen:phenotype_character>
            </phen:phenotype>
          </meta>
        </state>
      </states>
      <states id="sc8fb1bc6-14ab-4b24-806b-4d671f0a32c0">
        <state id="s6d402cda-b695-45f2-a6d3-7a7a5fb1b668" label="absent" symbol="0" about="#s6d402cda-b695-45f2-a6d3-7a7a5fb1b668">
          <meta xsi:type="LiteralMeta" property="ps:describesPhenotype">
            <phen:phenotype>
              <phen:phenotype_character>
                <phen:bearer>
                  <phen:typeref about="UBERON:0011634" />
                </phen:bearer>
                <phen:quality>
                  <phen:typeref about="PATO:0000462" />
                </phen:quality>
              </phen:phenotype_character>
            </phen:phenotype>
          </meta>
        </state>
      </states>
      <states id="s7c78d4be-f539-4c5f-a485-6996da7179f3">
        <state id="s8fc80f01-84ae-44ae-bca0-6c22c535ab3d" label="absent" symbol="0" about="#s8fc80f01-84ae-44ae-bca0-6c22c535ab3d">
          <meta xsi:type="LiteralMeta" property="ps:describesPhenotype">
            <phen:phenotype>
              <phen:phenotype_character>
                <phen:bearer>
                  <phen:typeref about="UBERON:2000240" />
                </phen:bearer>
                <phen:quality>
                  <phen:typeref about="PATO:0000462" />
                </phen:quality>
              </phen:phenotype_character>
            </phen:phenotype>
          </meta>
        </state>
      </states>
      <states id="sfcb22cd8-59d1-4ed0-bc40-4b2c29dcc50e">
        <state id="sac5c697d-01f4-487e-8ccd-dde98ada094b" label="absent" symbol="0" about="#sac5c697d-01f4-487e-8ccd-dde98ada094b">
          <meta xsi:type="LiteralMeta" property="ps:describesPhenotype">
            <phen:phenotype>
              <phen:phenotype_character>
                <phen:bearer>
                  <phen:typeref about="UBERON:2000452" />
                </phen:bearer>
                <phen:quality>
                  <phen:typeref about="PATO:0000462" />
                </phen:quality>
              </phen:phenotype_character>
            </phen:phenotype>
          </meta>
        </state>
      </states>
      <states id="sf81346d8-55c5-4486-8740-5a56efeff61d">
        <state id="s882ee3f6-4785-4c6f-af91-72686f8c39ac" label="absent" symbol="0" about="#s882ee3f6-4785-4c6f-af91-72686f8c39ac">
          <meta xsi:type="LiteralMeta" property="ps:describesPhenotype">
            <phen:phenotype>
              <phen:phenotype_character>
                <phen:bearer>
                  <phen:typeref about="UBERON:2001894" />
                </phen:bearer>
                <phen:quality>
                  <phen:typeref about="PATO:0000462" />
                </phen:quality>
              </phen:phenotype_character>
              <phen:phenotype_character>
                <phen:bearer>
                  <phen:typeref about="UBERON:2001895" />
                </phen:bearer>
                <phen:quality>
                  <phen:typeref about="PATO:0000462" />
                </phen:quality>
              </phen:phenotype_character>
              <phen:phenotype_character>
                <phen:bearer>
                  <phen:typeref about="UBERON:2001896" />
                </phen:bearer>
                <phen:quality>
                  <phen:typeref about="PATO:0000462" />
                </phen:quality>
              </phen:phenotype_character>
            </phen:phenotype>
          </meta>
        </state>
      </states>
      <states id="s9a0e1876-13f8-46ec-acca-5c05ad963974">
        <state id="sf9020e1d-cfa9-4661-82d1-dfd483f64481" label="absent" symbol="0" about="#sf9020e1d-cfa9-4661-82d1-dfd483f64481">
          <meta xsi:type="LiteralMeta" property="ps:describesPhenotype">
            <phen:phenotype>
              <phen:phenotype_character>
                <phen:bearer>
                  <phen:typeref about="UBERON:0010290" />
                </phen:bearer>
                <phen:quality>
                  <phen:typeref about="PATO:0000462" />
                </phen:quality>
              </phen:phenotype_character>
            </phen:phenotype>
          </meta>
        </state>
      </states>
      <states id="s9371a8fb-fbd4-40a9-9d0e-1f2567238553">
        <state id="sb63bcc21-4d6b-4dfe-93ff-c3b4fce2777f" label="absent" symbol="0" about="#sb63bcc21-4d6b-4dfe-93ff-c3b4fce2777f">
          <meta xsi:type="LiteralMeta" property="ps:describesPhenotype">
            <phen:phenotype>
              <phen:phenotype_character>
                <phen:bearer>
                  <phen:typeref about="UBERON:2000549" />
                </phen:bearer>
                <phen:quality>
                  <phen:typeref about="PATO:0000462" />
                </phen:quality>
              </phen:phenotype_character>
            </phen:phenotype>
          </meta>
        </state>
      </states>
      <states id="s15955938-90ff-4c4c-90eb-34a0b8658561">
        <state id="s33a74bd2-d2b4-4457-9885-b951c737fe68" label="absent" symbol="0" about="#s33a74bd2-d2b4-4457-9885-b951c737fe68">
          <meta xsi:type="LiteralMeta" property="ps:describesPhenotype">
            <phen:phenotype>
              <phen:phenotype_character>
                <phen:bearer>
                  <phen:typeref about="UBERON:2000410" />
                </phen:bearer>
                <phen:quality>
                  <phen:typeref about="PATO:0000462" />
                </phen:quality>
              </phen:phenotype_character>
            </phen:phenotype>
          </meta>
        </state>
      </states>
      <states id="sa69d331e-bba9-423a-af88-5ef323b57dc9">
        <state id="sc90f969c-e27d-454f-8881-607db651e6af" label="absent" symbol="0" about="#sc90f969c-e27d-454f-8881-607db651e6af">
          <meta xsi:type="LiteralMeta" property="ps:describesPhenotype">
            <phen:phenotype>
              <phen:phenotype_character>
                <phen:bearer>
                  <phen:typeref about="UBERON:4300092" />
                </phen:bearer>
                <phen:quality>
                  <phen:typeref about="PATO:0000462" />
                </phen:quality>
              </phen:phenotype_character>
            </phen:phenotype>
          </meta>
        </state>
      </states>
      <states id="se064fa32-b13a-48af-8484-293ec8fb9553">
        <state id="s5fb2e572-8930-4397-a052-ff79dd6be4ff" label="absent" symbol="0" />
      </states>
      <states id="s373f2774-fb81-4ef6-ae1e-f8012d659627">
        <state id="s1ab66990-9e80-4ff6-aecc-52ec8aaf32a7" label="absent" symbol="0" />
      </states>
      <states id="sa5919d06-174e-4b73-9fe2-ae39a9dcdf50">
        <state id="se2c38dc8-b3ab-478b-84df-67f9e2b9e7df" label="absent" symbol="0" about="#se2c38dc8-b3ab-478b-84df-67f9e2b9e7df">
          <meta xsi:type="LiteralMeta" property="ps:describesPhenotype">
            <phen:phenotype>
              <phen:phenotype_character>
                <phen:bearer>
                  <phen:typeref about="UBERON:4300214" />
                </phen:bearer>
                <phen:quality>
                  <phen:typeref about="PATO:0000462" />
                </phen:quality>
              </phen:phenotype_character>
              <phen:phenotype_character>
                <phen:bearer>
                  <phen:typeref about="UBERON:4300217" />
                </phen:bearer>
                <phen:quality>
                  <phen:typeref about="PATO:0000462" />
                </phen:quality>
              </phen:phenotype_character>
              <phen:phenotype_character>
                <phen:bearer>
                  <phen:typeref about="UBERON:4300218" />
                </phen:bearer>
                <phen:quality>
                  <phen:typeref about="PATO:0000462" />
                </phen:quality>
              </phen:phenotype_character>
              <phen:phenotype_character>
                <phen:bearer>
                  <phen:typeref about="UBERON:4300219" />
                </phen:bearer>
                <phen:quality>
                  <phen:typeref about="PATO:0000462" />
                </phen:quality>
              </phen:phenotype_character>
              <phen:phenotype_character>
                <phen:bearer>
                  <phen:typeref about="UBERON:4300220" />
                </phen:bearer>
                <phen:quality>
                  <phen:typeref about="PATO:0000462" />
                </phen:quality>
              </phen:phenotype_character>
              <phen:phenotype_character>
                <phen:bearer>
                  <phen:typeref about="UBERON:4300221" />
                </phen:bearer>
                <phen:quality>
                  <phen:typeref about="PATO:0000462" />
                </phen:quality>
              </phen:phenotype_character>
            </phen:phenotype>
          </meta>
        </state>
      </states>
      <states id="s9f066984-ea6e-4c22-90be-83afe6b4ea77">
        <state id="s47015462-722e-417e-a994-753442d124a0" label="absent" symbol="0" about="#s47015462-722e-417e-a994-753442d124a0">
          <meta xsi:type="LiteralMeta" property="ps:describesPhenotype">
            <phen:phenotype>
              <phen:phenotype_character>
                <phen:bearer>
                  <phen:typeref about="UBERON:2101613" />
                </phen:bearer>
                <phen:quality>
                  <phen:typeref about="PATO:0000462" />
                </phen:quality>
              </phen:phenotype_character>
              <phen:phenotype_character>
                <phen:bearer>
                  <phen:typeref about="UBERON:2100936" />
                </phen:bearer>
                <phen:quality>
                  <phen:typeref about="PATO:0000462" />
                </phen:quality>
              </phen:phenotype_character>
              <phen:phenotype_character>
                <phen:bearer>
                  <phen:typeref about="UBERON:2101614" />
                </phen:bearer>
                <phen:quality>
                  <phen:typeref about="PATO:0000462" />
                </phen:quality>
              </phen:phenotype_character>
              <phen:phenotype_character>
                <phen:bearer>
                  <phen:typeref about="UBERON:2100646" />
                </phen:bearer>
                <phen:quality>
                  <phen:typeref about="PATO:0000462" />
                </phen:quality>
              </phen:phenotype_character>
            </phen:phenotype>
          </meta>
        </state>
      </states>
      <states id="s94eb6a8a-1ec4-4beb-8b88-e4828c6b193d">
        <state id="s49537f51-026a-482d-a162-75904b91f18b" label="absent" symbol="0" about="#s49537f51-026a-482d-a162-75904b91f18b">
          <meta xsi:type="LiteralMeta" property="ps:describesPhenotype">
            <phen:phenotype>
              <phen:phenotype_character>
                <phen:bearer>
                  <phen:typeref about="UBERON:2000507" />
                </phen:bearer>
                <phen:quality>
                  <phen:typeref about="PATO:0000462" />
                </phen:quality>
              </phen:phenotype_character>
            </phen:phenotype>
          </meta>
        </state>
      </states>
      <states id="s33d86304-350d-49ec-993d-a1caf7c85612">
        <state id="s9581fa6e-e7bb-4fd0-992f-b5c025b50b91" label="absent" symbol="0" about="#s9581fa6e-e7bb-4fd0-992f-b5c025b50b91">
          <meta xsi:type="LiteralMeta" property="ps:describesPhenotype">
            <phen:phenotype>
              <phen:phenotype_character>
                <phen:bearer>
                  <phen:typeref about="UBERON:2000350" />
                </phen:bearer>
                <phen:quality>
                  <phen:typeref about="PATO:0000462" />
                </phen:quality>
              </phen:phenotype_character>
            </phen:phenotype>
          </meta>
        </state>
      </states>
      <states id="see107e0f-90fb-4492-a38b-9ceba331d058">
        <state id="sd6dc30bd-269f-41ce-80aa-a2c5bf7422c6" label="absent" symbol="0" about="#sd6dc30bd-269f-41ce-80aa-a2c5bf7422c6">
          <meta xsi:type="LiteralMeta" property="ps:describesPhenotype">
            <phen:phenotype>
              <phen:phenotype_character>
                <phen:bearer>
                  <phen:typeref about="UBERON:2002109" />
                </phen:bearer>
                <phen:quality>
                  <phen:typeref about="PATO:0000462" />
                </phen:quality>
              </phen:phenotype_character>
            </phen:phenotype>
          </meta>
        </state>
      </states>
      <states id="s4b8d4c48-a28c-48f8-bd58-84333a3bf678">
        <state id="sd008cbd1-6a0b-4802-8a41-1a8a497cc836" label="absent" symbol="0" about="#sd008cbd1-6a0b-4802-8a41-1a8a497cc836">
          <meta xsi:type="LiteralMeta" property="ps:describesPhenotype">
            <phen:phenotype>
              <phen:phenotype_character>
                <phen:bearer>
                  <phen:typeref about="UBERON:0007380" />
                </phen:bearer>
                <phen:quality>
                  <phen:typeref about="PATO:0000462" />
                </phen:quality>
              </phen:phenotype_character>
            </phen:phenotype>
          </meta>
        </state>
      </states>
      <char id="c367d0b2c-8ce1-4c44-8c5f-f81ac1b3ff89" label="Kinethmoid (and kinethmoid cartilage)" states="sf9469009-7a2c-4251-b3be-19a41ea1e579" />
      <char id="c4f108375-b8de-4ae6-97a1-b8e6928f0743" label="Preethmoid" states="s4b2c92a4-b361-40eb-a633-c22cdc0f210f" />
      <char id="c1a218126-6ac4-4c67-95af-edb08452a643" label="Vomer" states="s971ae930-fb51-407e-b308-2c58f049be5e" />
      <char id="c0ac57118-cb5a-42fc-83db-5ee3c1f76a69" label="Dermethmoid" states="s542293a2-19dd-43e8-8f7b-e7844772baff" />
      <char id="cd6e6dd5c-7d45-4277-999e-c3d7f2db294d" label="Nasal" states="sb82a1563-20c3-4233-9307-dcbceba81305" />
      <char id="c9e902ee2-243f-4b26-a5a4-9cb529123540" label="Parietal" states="sf3fd0ca6-fe61-4337-bbfc-7580626980ee" />
      <char id="c34401e4e-e888-44d5-bdcc-c1187dda85ca" label="Intercalar" states="s116cec39-7c09-4da8-8697-de563b70fafb" />
      <char id="c799902c0-332d-48f0-9583-c6e78787203c" label="Extrascapular" states="sc8210009-5c34-4122-b1ee-5979d7bb70a6" />
      <char id="c693b1c2b-dcc6-4bb7-81dc-06814852e7f5" label="Infraorbitals 2-5" states="sef65cd6b-2ac3-4d03-8e21-dbd499d7ef80" />
      <char id="c7b09ba90-b6a6-421c-ae02-48239c7fe45b" label="Ectopterygoid" states="sc8fb1bc6-14ab-4b24-806b-4d671f0a32c0" />
      <char id="c79600ce0-0942-4a06-8e51-e29f3062574b" label="Metapterygoid" states="s7c78d4be-f539-4c5f-a485-6996da7179f3" />
      <char id="c63a09478-b3c8-4142-9b21-171786324594" label="Urohyal" states="sfcb22cd8-59d1-4ed0-bc40-4b2c29dcc50e" />
      <char id="ccf7b7635-37c6-4fc7-81ff-16c3379afa93" label="Hypobranchials 1-3" states="sf81346d8-55c5-4486-8740-5a56efeff61d" />
      <char id="c7e738b01-27c4-4bf1-b2e3-a7dca2c5d31c" label="Sclerotic bones" states="s9a0e1876-13f8-46ec-acca-5c05ad963974" />
      <char id="c59d66835-bb46-43c0-a160-d86a2a94764d" label="Posttemporal" states="s9371a8fb-fbd4-40a9-9d0e-1f2567238553" />
      <char id="c3547cfd9-3b89-4554-ad35-796f51bdbe19" label="Postcleithrum" states="s15955938-90ff-4c4c-90eb-34a0b8658561" />
      <char id="c52eefbff-6bf8-4298-b845-7f15f01396ef" label="Mesocoracoid" states="sa69d331e-bba9-423a-af88-5ef323b57dc9" />
      <char id="c06a235d6-ba82-486b-b589-439de5fdd9bc" label="Pectoral radials 3-4 (pectoral radial cartilages 3–4)" about="#c06a235d6-ba82-486b-b589-439de5fdd9bc" states="se064fa32-b13a-48af-8484-293ec8fb9553">
        <meta xsi:type="LiteralMeta" property="rdfs:comment">NTR?</meta>
      </char>
      <char id="c8f34829d-8f9c-4b5e-83ca-451d59c33f48" label="Pelvic radials 1–3 (and pelvic radial cartilages 2–3)" about="#c8f34829d-8f9c-4b5e-83ca-451d59c33f48" states="s373f2774-fb81-4ef6-ae1e-f8012d659627">
        <meta xsi:type="LiteralMeta" property="rdfs:comment">NTR?</meta>
      </char>
      <char id="c1098905c-be6c-4457-ad65-01c0cb8bb11a" label="Supraneurals 2 and 5–9 (and supraneural cartilages 5–9)" states="sa5919d06-174e-4b73-9fe2-ae39a9dcdf50" />
      <char id="c35d3ca36-143a-45c8-adbf-cb633b8f0b23" label="Middle and distal radials in dorsal and anal fins" states="s9f066984-ea6e-4c22-90be-83afe6b4ea77" />
      <char id="c49af765c-e708-4e70-9389-c281156eee79" label="Epineurals" states="s94eb6a8a-1ec4-4beb-8b88-e4828c6b193d" />
      <char id="c6e8738fb-11e8-4673-be5c-7f0024e7072b" label="Epipleurals" states="s33d86304-350d-49ec-993d-a1caf7c85612" />
      <char id="c23700c0f-b455-416e-bf0a-b0109184bfac" label="Uroneural 2" states="see107e0f-90fb-4492-a38b-9ceba331d058" />
      <char id="c11d18de0-0dea-4494-bae9-dbe1fa253066" label="Scales" states="s4b8d4c48-a28c-48f8-bd58-84333a3bf678" />
    </format>
    <matrix>
      <row id="r42e48af6-fbc2-4191-84b6-af80291eff57" otu="t4c329efd-f251-48ef-b8ef-baa91e9ca0f7">
        <cell char="c367d0b2c-8ce1-4c44-8c5f-f81ac1b3ff89" state="s70694060-9eed-4442-93c8-c63248dd9d67" />
        <cell char="c4f108375-b8de-4ae6-97a1-b8e6928f0743" state="sc481e3f7-f37c-4bfc-926c-4830d18cffea" />
        <cell char="c1a218126-6ac4-4c67-95af-edb08452a643" state="s42913ffc-f344-4d37-acdf-555f2e27d77f" />
        <cell char="c0ac57118-cb5a-42fc-83db-5ee3c1f76a69" state="s641e47be-46c5-42f9-9e13-880db944b1a6" />
        <cell char="cd6e6dd5c-7d45-4277-999e-c3d7f2db294d" state="sdd87d207-a81c-4d3b-b885-dc2e2e2b3b3c" />
        <cell char="c9e902ee2-243f-4b26-a5a4-9cb529123540" state="s41d28048-1eff-49a8-bd85-881cf9997656" />
        <cell char="c34401e4e-e888-44d5-bdcc-c1187dda85ca" state="sa1bae812-6370-4aaa-9e97-472d6d87d74d" />
        <cell char="c799902c0-332d-48f0-9583-c6e78787203c" state="sf9cfa8d8-d7af-40b9-a0c3-d18bff86a115" />
        <cell char="c693b1c2b-dcc6-4bb7-81dc-06814852e7f5" state="sac6bf7f5-cbe3-410b-92ad-b8dd24d72e7c" />
        <cell char="c7b09ba90-b6a6-421c-ae02-48239c7fe45b" state="s6d402cda-b695-45f2-a6d3-7a7a5fb1b668" />
        <cell char="c79600ce0-0942-4a06-8e51-e29f3062574b" state="s8fc80f01-84ae-44ae-bca0-6c22c535ab3d" />
        <cell char="c63a09478-b3c8-4142-9b21-171786324594" state="sac5c697d-01f4-487e-8ccd-dde98ada094b" />
        <cell char="ccf7b7635-37c6-4fc7-81ff-16c3379afa93" state="s882ee3f6-4785-4c6f-af91-72686f8c39ac" />
        <cell char="c7e738b01-27c4-4bf1-b2e3-a7dca2c5d31c" state="sf9020e1d-cfa9-4661-82d1-dfd483f64481" />
        <cell char="c59d66835-bb46-43c0-a160-d86a2a94764d" state="sb63bcc21-4d6b-4dfe-93ff-c3b4fce2777f" />
        <cell char="c3547cfd9-3b89-4554-ad35-796f51bdbe19" state="s33a74bd2-d2b4-4457-9885-b951c737fe68" />
        <cell char="c52eefbff-6bf8-4298-b845-7f15f01396ef" state="sc90f969c-e27d-454f-8881-607db651e6af" />
        <cell char="c06a235d6-ba82-486b-b589-439de5fdd9bc" state="s5fb2e572-8930-4397-a052-ff79dd6be4ff" />
        <cell char="c8f34829d-8f9c-4b5e-83ca-451d59c33f48" state="s1ab66990-9e80-4ff6-aecc-52ec8aaf32a7" />
        <cell char="c1098905c-be6c-4457-ad65-01c0cb8bb11a" state="se2c38dc8-b3ab-478b-84df-67f9e2b9e7df" />
        <cell char="c35d3ca36-143a-45c8-adbf-cb633b8f0b23" state="s47015462-722e-417e-a994-753442d124a0" />
        <cell char="c49af765c-e708-4e70-9389-c281156eee79" state="s49537f51-026a-482d-a162-75904b91f18b" />
        <cell char="c6e8738fb-11e8-4673-be5c-7f0024e7072b" state="s9581fa6e-e7bb-4fd0-992f-b5c025b50b91" />
        <cell char="c23700c0f-b455-416e-bf0a-b0109184bfac" state="sd6dc30bd-269f-41ce-80aa-a2c5bf7422c6" />
        <cell char="c11d18de0-0dea-4494-bae9-dbe1fa253066" state="sd008cbd1-6a0b-4802-8a41-1a8a497cc836" />
      </row>
    </matrix>
  </characters>
  <trees id="t2bc09e80-13d0-42ca-8419-8054a2d5bd1b" otus="t611139a1-0277-4c63-8cc6-d586f0f518e9" />
  <trees id="t6263eed9-bc29-4f3a-9f9d-bb200815a0f3" otus="t611139a1-0277-4c63-8cc6-d586f0f518e9" />
</nexml>
